samvvvmk/__init__.py
samvvvmk/lib2.py
samvvvmk/lib3.py
samvvvmk-0.2.dist-info/METADATA
samvvvmk-0.2.dist-info/WHEEL
samvvvmk-0.2.dist-info/top_level.txt
samvvvmk-0.2.dist-info/RECORD
