Metadata-Version: 2.1
Name: samvvvmk
Version: 0.2
Summary: basic function
Home-page: http://github.com/storborg/funniest
Author: samvvv2002
Author-email: flyingcircus@example.com
License: MIT
Platform: UNKNOWN
